MANIFEST.in
README.md
setup.cfg
setup.py
examples/arithmetics_class.py
examples/arithmetics_module.py
plier/__init__.py
plier.egg-info/PKG-INFO
plier.egg-info/SOURCES.txt
plier.egg-info/dependency_links.txt
plier.egg-info/requires.txt
plier.egg-info/top_level.txt
plier/framework/__init__.py
plier/framework/lex.py
plier/framework/yacc.py
plier/utils/__init__.py
plier/utils/func.py
plier/utils/regex.py
plier/utils/trees.py