Metadata-Version: 1.1
Name: plier
Version: 0.1.0
Summary: Utilities for PLY (Python Lex & Yacc)
Home-page: https://github.com/haimoz/plier
Author: Haimo Zhang
Author-email: zh.hammer.dev@gmail.com
License: MIT
Platform: UNKNOWN
Classifier: Development Status :: 3 - Alpha
Classifier: Intended Audience :: Developers
Classifier: Intended Audience :: Science/Research
Classifier: License :: OSI Approved :: MIT License
Classifier: Programming Language :: Python :: 2 :: Only
Classifier: Topic :: Software Development :: Build Tools
Classifier: Topic :: Software Development :: Code Generators
Classifier: Topic :: Software Development :: Compilers
Classifier: Topic :: Software Development :: Interpreters
Classifier: Topic :: Software Development :: Pre-processors
Classifier: Topic :: Utilities
Requires: ply(>=3.8)
